Metadata-Version: 1.1
Name: py2exe-converter
Version: 1.0.0
Summary: Python to Exe file converter package
Home-page: https://github.com/alihussainia/Py2Exe-Converter
Author: Muhammad Ali
Author-email: malirashid1994@gmail.com
License: UNKNOWN
Download-URL: https://github.com/alihussainia/Py2Exe-Converter/archive/refs/tags/v1.0.0.tar.gz
Keywords: py2exe,pyinstaller,python to exe converter,converter
Platform: UNKNOWN
